{
  "biomes": [
    [
      {
        "type": "BIOME_DICT",
        "negate": true,
        "value": "overworld"
      },
      {
        "type": "BIOME_CATEGORY",
        "negate": true,
        "value": "ocean"
      },
      {
        "type": "BIOME_DICT",
        "negate": true,
        "value": "ocean"
      }
    ],
    [
      {
        "type": "REGISTRY_NAME",
        "negate": true,
        "value": "terralith:skylands_autumn"
      }
    ],
    [
      {
        "type": "REGISTRY_NAME",
        "negate": true,
        "value": "terralith:skylands_spring"
      }
    ],
    [
      {
        "type": "REGISTRY_NAME",
        "negate": true,
        "value": "terralith:skylands_summer"
      }
    ],
    [
      {
        "type": "REGISTRY_NAME",
        "negate": true,
        "value": "terralith:skylands_winter"
      }
    ]
  ]
}